wagtail_linksnippet/__init__.py
wagtail_linksnippet/richtext.py
wagtail_linksnippet/richtext_utils.py
wagtail_linksnippet/utils.py
wagtail_linksnippet/views_utils.py
wagtail_linksnippet/static/wagtail_linksnippet/js/modelChooser.js
wagtail_linksnippet-1.0.1.dist-info/LICENSE
wagtail_linksnippet-1.0.1.dist-info/METADATA
wagtail_linksnippet-1.0.1.dist-info/WHEEL
wagtail_linksnippet-1.0.1.dist-info/top_level.txt
wagtail_linksnippet-1.0.1.dist-info/RECORD
