Metadata-Version: 2.2
Name: wagtail_linksnippet
Version: 1.0.1
Summary: A Wagtail extension to open custom chooser from RichText Editor.
Home-page: https://github.com/fab10m/wagtail_linksnippet
Author: Fabio Marras
Author-email: fabio.marras@fintastico.com
License: MIT
Classifier: Development Status :: 4 - Beta
Classifier: Framework :: Django
Classifier: Framework :: Wagtail
Classifier: Programming Language :: Python :: 3.10
Classifier: License :: OSI Approved :: MIT License
Classifier: Operating System :: OS Independent
License-File: LICENSE
Requires-Dist: wagtail>=6.0
Requires-Dist: django>=4.2
Dynamic: author
Dynamic: author-email
Dynamic: classifier
Dynamic: description
Dynamic: description-content-type
Dynamic: home-page
Dynamic: license
Dynamic: requires-dist
Dynamic: summary
